TCRA/__init__.py
TCRA/fragility/Recovery.py
TCRA/fragility/__init__.py
TCRA/fragility/damageanalysis.py
TCRA/fragility/fragility_curves.py
TCRA/fragility/fragility_curves_epn.py
TCRA/fragility/fragility_rehab.py
TCRA/fragility/hurricane.py
TCRA/fragility/interactive.py
TCRA/fragility/montecarlosimulation.py
TCRA/fragility/plot.py
TCRA/simulation/Recovery.py
TCRA/simulation/__init__.py
TCRA/simulation/damageanalysis.py
TCRA/simulation/fragility_rehab.py
TCRA/simulation/hurricane.py
TCRA/simulation/interactive.py
TCRA/simulation/montecarlosimulation.py
TCRA/simulation/plot.py
cyclone_package-0.1.0.dist-info/LICENSE.md
cyclone_package-0.1.0.dist-info/METADATA
cyclone_package-0.1.0.dist-info/WHEEL
cyclone_package-0.1.0.dist-info/top_level.txt
cyclone_package-0.1.0.dist-info/RECORD
